trying_dep_vuln/__init__.py
trying_dep_vuln/command_line.py
trying_dep_vuln/greet.py
trying_dep_vuln-2337.1.dist-info/METADATA
trying_dep_vuln-2337.1.dist-info/WHEEL
trying_dep_vuln-2337.1.dist-info/entry_points.txt
trying_dep_vuln-2337.1.dist-info/top_level.txt
trying_dep_vuln-2337.1.dist-info/RECORD
